hyperqueue-0.24.0.dist-info/METADATA
hyperqueue-0.24.0.dist-info/WHEEL
hyperqueue/utils/package.py
hyperqueue/utils/string.py
hyperqueue/utils/__init__.py
hyperqueue/output.py
hyperqueue/task/__init__.py
hyperqueue/task/task.py
hyperqueue/task/program.py
hyperqueue/task/function/wrapper.py
hyperqueue/task/function/__init__.py
hyperqueue/__init__.py
hyperqueue/validation.py
hyperqueue/client.py
hyperqueue/ffi/cluster.py
hyperqueue/ffi/__init__.py
hyperqueue/ffi/client.py
hyperqueue/ffi/protocol.py
hyperqueue/common.py
hyperqueue/cluster/__init__.py
hyperqueue/visualization.py
hyperqueue/job.py
hyperqueue/hyperqueue.abi3.so
hyperqueue-0.24.0.dist-info/RECORD
